cayolargo/__init__.py
cayolargo/cex.py
cayolargo/cmc.py
cayolargo/mykeys.py
cayolargo-0.1.1.dist-info/LICENSE
cayolargo-0.1.1.dist-info/METADATA
cayolargo-0.1.1.dist-info/WHEEL
cayolargo-0.1.1.dist-info/top_level.txt
cayolargo-0.1.1.dist-info/RECORD
