Metadata-Version: 2.1
Name: cayolargo
Version: 0.1.1
Summary: cayolargo by Halcyon Waters
Home-page: https://halcyonwaters.com/
Author: HalcyonWaters
Author-email: halcyonwaterscom@gmail.com
License: MIT
License-File: LICENSE
Requires-Dist: numpy
Requires-Dist: pandas
Requires-Dist: python-binance==1.0.17
Requires-Dist: matplotlib
Requires-Dist: requests
